gutenberg/__init__.py
gutenberg/main.py
gutenberg/models.py
py_gutenberg-1.0.3.dist-info/LICENSE
py_gutenberg-1.0.3.dist-info/METADATA
py_gutenberg-1.0.3.dist-info/WHEEL
py_gutenberg-1.0.3.dist-info/top_level.txt
py_gutenberg-1.0.3.dist-info/RECORD
