Metadata-Version: 2.1
Name: py-gutenberg
Version: 1.0.3
Summary: A library to access the Project Gutenberg API
Author-email: Peter Rauscher <peterrauscher@protonmail.com>
Project-URL: Homepage, https://github.com/peterrauscher/gutenberg-py
Project-URL: Bug Tracker, https://github.com/peterrauscher/gutenberg-py/issues
Project-URL: Source Code, https://github.com/peterrauscher/gutenberg-py
Project-URL: Funding, https://ko-fi.com/peterrauscher
Classifier: Development Status :: 5 - Production/Stable
Classifier: Intended Audience :: Developers
Classifier: Topic :: Software Development :: Build Tools
Classifier: Programming Language :: Python
Classifier: Programming Language :: Python :: 3
Classifier: Programming Language :: Python :: 3.7
Classifier: Programming Language :: Python :: 3.8
Classifier: Programming Language :: Python :: 3.9
Classifier: Programming Language :: Python :: 3.10
Classifier: Programming Language :: Python :: 3.11
Classifier: Programming Language :: Python :: 3 :: Only
Classifier: License :: OSI Approved :: MIT License
Classifier: Operating System :: OS Independent
Classifier: Natural Language :: English
Requires-Python: >=3.7
License-File: LICENSE
